LICENSE
MANIFEST.in
README.md
pyproject.toml
setup.py
tlylt/__init__.py
tlylt.egg-info/PKG-INFO
tlylt.egg-info/SOURCES.txt
tlylt.egg-info/dependency_links.txt
tlylt.egg-info/entry_points.txt
tlylt.egg-info/requires.txt
tlylt.egg-info/top_level.txt
tlylt/scripts/__init__.py
tlylt/scripts/cli.py