Metadata-Version: 2.1
Name: tlylt
Version: 0.0.3
Summary: A collection of scripts for daily use.
Author: Liu Yongliang
Author-email: liu_yongliang@hotmail.com
License-File: LICENSE
